xbatcher/__init__.py
xbatcher/accessors.py
xbatcher/generators.py
xbatcher/testing.py
xbatcher/loaders/__init__.py
xbatcher/loaders/keras.py
xbatcher/loaders/torch.py
xbatcher/tests/__init__.py
xbatcher/tests/test_accessors.py
xbatcher/tests/test_generators.py
xbatcher/tests/test_keras_loaders.py
xbatcher/tests/test_print_versions.py
xbatcher/tests/test_torch_loaders.py
xbatcher/util/__init__.py
xbatcher/util/print_versions.py
xbatcher-0.4.0.dist-info/LICENSE
xbatcher-0.4.0.dist-info/METADATA
xbatcher-0.4.0.dist-info/WHEEL
xbatcher-0.4.0.dist-info/top_level.txt
xbatcher-0.4.0.dist-info/RECORD
