Metadata-Version: 2.1
Name: xbatcher
Version: 0.4.0
Summary: Batch generation from Xarray objects
Author-email: xbatcher Developers <rpa@ldeo.columbia.edu>
License: Apache
Project-URL: documentation, https://xbatcher.readthedocs.io/en/latest/
Project-URL: repository, https://github.com/xarray-contrib/xbatcher
Classifier: Development Status :: 4 - Beta
Classifier: License :: OSI Approved :: Apache Software License
Classifier: Operating System :: OS Independent
Classifier: Intended Audience :: Science/Research
Classifier: Programming Language :: Python
Classifier: Programming Language :: Python :: 3
Classifier: Programming Language :: Python :: 3.10
Classifier: Programming Language :: Python :: 3.11
Classifier: Programming Language :: Python :: 3.12
Classifier: Topic :: Scientific/Engineering
Requires-Python: >=3.10
License-File: LICENSE
Requires-Dist: dask
Requires-Dist: numpy
Requires-Dist: xarray
Provides-Extra: dev
Requires-Dist: adlfs ; extra == 'dev'
Requires-Dist: asv ; extra == 'dev'
Requires-Dist: coverage ; extra == 'dev'
Requires-Dist: pytest ; extra == 'dev'
Requires-Dist: pytest-cov ; extra == 'dev'
Requires-Dist: tensorflow ; extra == 'dev'
Requires-Dist: torch ; extra == 'dev'
Requires-Dist: zarr ; extra == 'dev'
Provides-Extra: tensorflow
Requires-Dist: tensorflow ; extra == 'tensorflow'
Provides-Extra: torch
Requires-Dist: torch ; extra == 'torch'
